public/__init__.py
public/modules.py
public/private.py
public/public.py
public/py.typed
public/types.py
atpublic-6.0.dist-info/METADATA
atpublic-6.0.dist-info/WHEEL
atpublic-6.0.dist-info/licenses/LICENSE
atpublic-6.0.dist-info/RECORD
