Metadata-Version: 2.4
Name: atpublic
Version: 6.0
Summary: Keep all y'all's __all__'s in sync
Project-URL: Home Page, https://public.readthedocs.io
Project-URL: Documentation, https://public.readthedocs.io
Project-URL: Source, https://gitlab.com/warsaw/public.git
Project-URL: Bug Tracker, https://gitlab.com/warsaw/public/issues
Author-email: Barry Warsaw <barry@python.org>
License: Apache-2.0
License-File: LICENSE
Keywords: __all__,private,public
Classifier: Development Status :: 5 - Production/Stable
Classifier: Development Status :: 6 - Mature
Classifier: Intended Audience :: Developers
Classifier: License :: OSI Approved :: Apache Software License
Classifier: Operating System :: MacOS :: MacOS X
Classifier: Operating System :: Microsoft :: Windows
Classifier: Operating System :: POSIX
Classifier: Programming Language :: Python
Classifier: Programming Language :: Python :: 3
Classifier: Topic :: Software Development :: Libraries
Classifier: Topic :: Software Development :: Libraries :: Python Modules
Classifier: Topic :: Utilities
Requires-Python: >=3.9
